{
  "term": "202408",
  "subjectCode": "LMC",
  "courseNumber": "6399",
  "courseId": "LMC 6399",
  "title": "Discovery &amp; Invention",
  "description": "Required course for all DM majors. The purpose of this course is to give students a suite of methods they can use in professional settings to discover opportunities for inventive new computational products and services. It complements the design and production skills developed in 6310 and 6313 with applied research skills. For students in the MS DM and MS HCI programs it will also help them in the development of their MS proposals. Students cannot receive credit for LMC 6399 and LCC 6399.",
  "creditHours": "3",
  "restrictions": [
    "__HEADER_0__Cannot be enrolled in one of the following Levels:",
    "__DETAIL_0__Undergraduate Semester (US)",
    "__HEADER_1__Must be enrolled in one of the following Campuses:",
    "__DETAIL_1__Georgia Tech-Atlanta * (A)"
  ],
  "corequisites": [],
  "prerequisites": [],
  "lastUpdated": "2025-08-20T02:41:38.862Z"
}
