{
  "term": "202508",
  "subjectCode": "ARBC",
  "courseNumber": "1501",
  "courseId": "ARBC 1501",
  "title": "Understand Arab Culture",
  "description": "Arab beliefs and values regarding topics such as religion, society, family, the dynamics between men and women, and social norms are discussed.  Taught in English.",
  "creditHours": "3",
  "restrictions": [
    "__HEADER_0__Cannot be enrolled in one of the following Levels:",
    "__DETAIL_0__Graduate Semester (GS)",
    "__HEADER_1__Must be enrolled in one of the following Campuses:",
    "__DETAIL_1__Georgia Tech-Atlanta * (A)"
  ],
  "corequisites": [],
  "prerequisites": [],
  "lastUpdated": "2025-08-20T02:36:13.934Z"
}
