{
  "term": "202508",
  "subjectCode": "ECE",
  "courseNumber": "8900",
  "courseId": "ECE 8900",
  "title": "Special Problems",
  "description": "No course description is available.",
  "creditHours": "1 to 21",
  "restrictions": [
    "__HEADER_0__Cannot be enrolled in one of the following Levels:",
    "__DETAIL_0__Undergraduate Semester (US)",
    "__HEADER_1__Must be enrolled in one of the following Majors:",
    "__DETAIL_1__Bioengineering (BIOE)",
    "__DETAIL_1__Electrical & Computer Engr (ECE)",
    "__DETAIL_1__Machine Learning (MLRN)",
    "__DETAIL_1__Robotics (ROBO)",
    "__HEADER_2__Must be enrolled in one of the following Campuses:",
    "__DETAIL_2__Georgia Tech-Atlanta * (A)"
  ],
  "corequisites": [],
  "prerequisites": [],
  "lastUpdated": "2025-08-20T02:39:57.256Z"
}
