{
  "term": "202502",
  "subjectCode": "CSE",
  "courseNumber": "7850",
  "courseId": "CSE 7850",
  "title": "ML in Comp Bio",
  "description": "Introduction to modern machine learning techniques in computational biology",
  "creditHours": "3",
  "restrictions": [
    "__HEADER_0__Cannot be enrolled in one of the following Levels:",
    "__DETAIL_0__Undergraduate Semester (US)",
    "__HEADER_1__Must be enrolled in one of the following Campuses:",
    "__DETAIL_1__Georgia Tech-Atlanta * (A)"
  ],
  "corequisites": [],
  "prerequisites": [],
  "lastUpdated": "2025-08-20T02:37:22.192Z"
}
