{
  "term": "202502",
  "subjectCode": "LMC",
  "courseNumber": "6313",
  "courseId": "LMC 6313",
  "title": "Prin of Interaction Desi",
  "description": "Explores visual media through a mutually instructive and integrated interplay between critical analyses and the creation of digital artifacts. Students cannot receive credit for LMC 6313 and LCC 6313.",
  "creditHours": "3",
  "restrictions": [
    "__HEADER_0__Cannot be enrolled in one of the following Levels:",
    "__DETAIL_0__Undergraduate Semester (US)",
    "__HEADER_1__Must be enrolled in one of the following Campuses:",
    "__DETAIL_1__Georgia Tech-Atlanta * (A)"
  ],
  "corequisites": [],
  "prerequisites": [],
  "lastUpdated": "2025-08-20T02:41:13.549Z"
}
