{
  "term": "202502",
  "subjectCode": "MP",
  "courseNumber": "6204",
  "courseId": "MP 6204",
  "title": "Radiation Therapy Phys",
  "description": "Measurement and calculation of absorbed dose, dose distributions, treatment planning, photon teletherapy, electron teletherapy, brachytherapy, clinical linear accelerators, quality assurance.",
  "creditHours": "4",
  "restrictions": [
    "__HEADER_0__Cannot be enrolled in one of the following Levels:",
    "__DETAIL_0__Undergraduate Semester (US)",
    "__HEADER_1__Must be enrolled in one of the following Campuses:",
    "__DETAIL_1__Georgia Tech-Atlanta * (A)"
  ],
  "corequisites": [],
  "prerequisites": "HP 6756 Graduate Semester Minimum Grade of D or MP 6756 Graduate Semester Minimum Grade of D or NRE 6756 Graduate Semester Minimum Grade of D",
  "lastUpdated": "2025-08-20T02:42:54.094Z"
}
