{
  "term": "202502",
  "subjectCode": "MUSI",
  "courseNumber": "3121",
  "courseId": "MUSI 3121",
  "title": "Concert Band",
  "description": "An advanced instrumental ensemble performing traditional and contemporary wind literature. Offered to all students with woodwind, brass, or percussion experience. Audition required.",
  "creditHours": "1",
  "restrictions": [
    "__HEADER_0__Must be enrolled in one of the following Campuses:",
    "__DETAIL_0__Georgia Tech-Atlanta * (A)"
  ],
  "corequisites": [],
  "prerequisites": [],
  "lastUpdated": "2025-08-20T02:42:59.141Z"
}
