{
  "term": "202505",
  "subjectCode": "ID",
  "courseNumber": "2401",
  "courseId": "ID 2401",
  "title": "Visual Design Thinking",
  "description": "Introduction to techniques to help designers build a vocabulary to support effective visual communication including fundamentals of layout, sketching, rendering, schematics, information graphics & storyboarding.",
  "creditHours": "3",
  "restrictions": [
    "__HEADER_0__Cannot be enrolled in one of the following Levels:",
    "__DETAIL_0__Graduate Semester (GS)",
    "__HEADER_1__Must be enrolled in one of the following Campuses:",
    "__DETAIL_1__Georgia Tech-Atlanta * (A)"
  ],
  "corequisites": [],
  "prerequisites": [],
  "lastUpdated": "2025-08-20T02:40:51.401Z"
}
